rgfrosh/__init__.py
rgfrosh/constants.py
rgfrosh/errors.py
rgfrosh/shock.py
rgfrosh/thermo.py
rgfrosh-0.3.0.dist-info/LICENSE
rgfrosh-0.3.0.dist-info/METADATA
rgfrosh-0.3.0.dist-info/WHEEL
rgfrosh-0.3.0.dist-info/top_level.txt
rgfrosh-0.3.0.dist-info/RECORD
