Metadata-Version: 2.1
Name: rgfrosh
Version: 0.3.0
Summary: A frozen shock solver for ideal and real gas equations of state.
Home-page: https://github.com/VasuLab/RGFROSH
Author: Cory Kinney
Author-email: corykinney@ucf.edu
License: MIT
Platform: any
Classifier: Programming Language :: Python :: 3
Classifier: Programming Language :: Python :: 3.8
Classifier: Programming Language :: Python :: 3.9
Classifier: Programming Language :: Python :: 3.10
Classifier: Programming Language :: Python :: 3.11
Classifier: Programming Language :: Python :: 3.12
Classifier: License :: OSI Approved :: MIT License
Classifier: Operating System :: OS Independent
Requires-Python: >=3.8
License-File: LICENSE
Requires-Dist: attrs >=20.1.0
Requires-Dist: numpy >=1.10.0
Requires-Dist: tabulate >=0.9.0
